coze/__init__.py
coze/coze.py
coze-0.0.1.dist-info/METADATA
coze-0.0.1.dist-info/WHEEL
coze-0.0.1.dist-info/top_level.txt
coze-0.0.1.dist-info/RECORD
