Metadata-Version: 2.1
Name: coze
Version: 0.0.1
Summary: use coze api in python
Home-page: https://github.com/lyhue1991/coze
Author: lyhue1991
Author-email: lyhue1991@163.com
Keywords: coze
Classifier: Programming Language :: Python :: 3
Classifier: License :: OSI Approved :: MIT License
Classifier: Operating System :: OS Independent
Requires-Python: >=3.0
